{"rows":[{"c":[{"v":"Date(2012,8,26,0,14,7)"},{"v":18.98},{"v":19.0},null,{"v":19.91},{"v":19.33},null]},{"c":[{"v":"Date(2012,8,26,0,16,14)"},{"v":18.98},{"v":19.0},null,{"v":19.89},{"v":19.26},null]},{"c":[{"v":"Date(2012,8,26,0,18,21)"},{"v":18.98},{"v":19.0},null,{"v":19.88},{"v":19.19},null]},{"c":[{"v":"Date(2012,8,26,0,20,28)"},{"v":18.98},{"v":19.0},null,{"v":19.88},{"v":19.24},null]},{"c":[{"v":"Date(2012,8,26,0,22,31)"},{"v":18.98},{"v":19.0},null,{"v":19.88},{"v":19.2},null]},{"c":[{"v":"Date(2012,8,26,0,24,39)"},{"v":18.99},{"v":19.0},null,{"v":19.85},{"v":19.04},null]},{"c":[{"v":"Date(2012,8,26,0,26,46)"},{"v":18.99},{"v":19.0},null,{"v":19.82},{"v":19.1},null]},{"c":[{"v":"Date(2012,8,26,0,28,53)"},{"v":18.99},{"v":19.0},null,{"v":19.82},{"v":19.04},null]},{"c":[{"v":"Date(2012,8,26,0,31,1)"},{"v":19.0},{"v":19.0},null,{"v":19.81},{"v":18.93},null]},{"c":[{"v":"Date(2012,8,26,0,33,8)"},{"v":18.99},{"v":19.0},null,{"v":19.81},{"v":18.98},null]},{"c":[{"v":"Date(2012,8,26,0,35,10)"},{"v":19.0},{"v":19.0},null,{"v":19.81},{"v":18.98},null]},{"c":[{"v":"Date(2012,8,26,0,36,14)"},{"v":18.99},{"v":19.0},{"v":"Beer temperature setting changed to  18.00 by profile temperature profile."},{"v":19.81},{"v":19.05},null]},{"c":[{"v":"Date(2012,8,26,0,38,20)"},{"v":18.99},{"v":18.0},null,{"v":19.8},{"v":4.0},null]},{"c":[{"v":"Date(2012,8,26,0,40,27)"},{"v":19.0},{"v":18.0},null,{"v":19.62},{"v":4.0},null]},{"c":[{"v":"Date(2012,8,26,0,42,34)"},{"v":18.99},{"v":18.0},null,{"v":19.18},{"v":4.0},null]},{"c":[{"v":"Date(2012,8,26,0,44,41)"},{"v":18.99},{"v":18.0},null,{"v":18.55},{"v":4.0},null]},{"c":[{"v":"Date(2012,8,26,0,46,44)"},{"v":18.99},{"v":18.0},null,{"v":17.76},{"v":4.0},null]},{"c":[{"v":"Date(2012,8,26,0,48,52)"},{"v":18.99},{"v":18.0},null,{"v":16.89},{"v":4.0},null]},{"c":[{"v":"Date(2012,8,26,0,50,55)"},{"v":18.95},{"v":18.0},null,{"v":16.18},{"v":4.0},null]},{"c":[{"v":"Date(2012,8,26,0,53,3)"},{"v":18.95},{"v":18.0},null,{"v":15.45},{"v":4.08},null]},{"c":[{"v":"Date(2012,8,26,0,55,10)"},{"v":18.94},{"v":18.0},null,{"v":14.77},{"v":4.27},null]},{"c":[{"v":"Date(2012,8,26,0,57,17)"},{"v":18.93},{"v":18.0},null,{"v":14.18},{"v":4.45},null]},{"c":[{"v":"Date(2012,8,26,0,59,25)"},{"v":18.92},{"v":18.0},null,{"v":13.58},{"v":4.57},null]},{"c":[{"v":"Date(2012,8,26,1,1,29)"},{"v":18.89},{"v":18.0},null,{"v":13.1},{"v":5.39},null]},{"c":[{"v":"Date(2012,8,26,1,3,36)"},{"v":18.88},{"v":18.0},null,{"v":12.59},{"v":5.88},null]},{"c":[{"v":"Date(2012,8,26,1,5,44)"},{"v":18.84},{"v":18.0},null,{"v":12.14},{"v":6.49},null]},{"c":[{"v":"Date(2012,8,26,1,7,51)"},{"v":18.81},{"v":18.0},null,{"v":11.73},{"v":7.22},null]},{"c":[{"v":"Date(2012,8,26,1,9,58)"},{"v":18.8},{"v":18.0},null,{"v":11.35},{"v":7.53},null]},{"c":[{"v":"Date(2012,8,26,1,12,5)"},{"v":18.75},{"v":18.0},null,{"v":11.01},{"v":8.5},null]},{"c":[{"v":"Date(2012,8,26,1,14,14)"},{"v":18.71},{"v":18.0},null,{"v":10.71},{"v":9.15},null]},{"c":[{"v":"Date(2012,8,26,1,16,21)"},{"v":18.69},{"v":18.0},null,{"v":10.56},{"v":9.83},null]},{"c":[{"v":"Date(2012,8,26,1,18,28)"},{"v":18.64},{"v":18.0},null,{"v":10.62},{"v":10.57},null]},{"c":[{"v":"Date(2012,8,26,1,20,35)"},{"v":18.62},{"v":18.0},null,{"v":10.87},{"v":10.99},null]},{"c":[{"v":"Date(2012,8,26,1,22,39)"},{"v":18.58},{"v":18.0},null,{"v":11.18},{"v":11.56},null]},{"c":[{"v":"Date(2012,8,26,1,24,47)"},{"v":18.56},{"v":18.0},null,{"v":11.54},{"v":11.91},null]},{"c":[{"v":"Date(2012,8,26,1,26,50)"},{"v":18.55},{"v":18.0},null,{"v":11.88},{"v":11.86},null]},{"c":[{"v":"Date(2012,8,26,1,28,57)"},{"v":18.5},{"v":18.0},null,{"v":12.22},{"v":12.58},null]},{"c":[{"v":"Date(2012,8,26,1,31,4)"},{"v":18.5},{"v":18.0},null,{"v":12.54},{"v":12.57},null]},{"c":[{"v":"Date(2012,8,26,1,33,12)"},{"v":18.46},{"v":18.0},null,{"v":12.85},{"v":12.83},null]},{"c":[{"v":"Date(2012,8,26,1,35,19)"},{"v":18.44},{"v":18.0},null,{"v":13.1},{"v":13.33},null]},{"c":[{"v":"Date(2012,8,26,1,37,26)"},{"v":18.43},{"v":18.0},null,{"v":13.36},{"v":13.25},null]},{"c":[{"v":"Date(2012,8,26,1,39,33)"},{"v":18.41},{"v":18.0},null,{"v":13.58},{"v":13.17},null]},{"c":[{"v":"Date(2012,8,26,1,41,39)"},{"v":18.38},{"v":18.0},null,{"v":13.68},{"v":13.58},null]},{"c":[{"v":"Date(2012,8,26,1,43,46)"},{"v":18.38},{"v":18.0},null,{"v":13.56},{"v":13.82},null]},{"c":[{"v":"Date(2012,8,26,1,45,53)"},{"v":18.37},{"v":18.0},null,{"v":13.56},{"v":13.74},null]},{"c":[{"v":"Date(2012,8,26,1,48,0)"},{"v":18.35},{"v":18.0},null,{"v":13.62},{"v":13.91},null]},{"c":[{"v":"Date(2012,8,26,1,50,8)"},{"v":18.32},{"v":18.0},null,{"v":13.76},{"v":14.6},null]},{"c":[{"v":"Date(2012,8,26,1,52,15)"},{"v":18.31},{"v":18.0},null,{"v":13.9},{"v":14.68},null]},{"c":[{"v":"Date(2012,8,26,1,54,22)"},{"v":18.31},{"v":18.0},null,{"v":14.06},{"v":14.59},null]},{"c":[{"v":"Date(2012,8,26,1,56,29)"},{"v":18.29},{"v":18.0},null,{"v":14.2},{"v":14.71},null]},{"c":[{"v":"Date(2012,8,26,1,58,36)"},{"v":18.26},{"v":18.0},null,{"v":14.37},{"v":15.17},null]},{"c":[{"v":"Date(2012,8,26,2,0,39)"},{"v":18.25},{"v":18.0},null,{"v":14.54},{"v":15.44},null]},{"c":[{"v":"Date(2012,8,26,2,2,47)"},{"v":18.25},{"v":18.0},null,{"v":14.7},{"v":15.35},null]},{"c":[{"v":"Date(2012,8,26,2,4,54)"},{"v":18.25},{"v":18.0},null,{"v":14.87},{"v":15.2},null]},{"c":[{"v":"Date(2012,8,26,2,7,1)"},{"v":18.23},{"v":18.0},null,{"v":15.03},{"v":15.26},null]},{"c":[{"v":"Date(2012,8,26,2,9,8)"},{"v":18.21},{"v":18.0},null,{"v":15.19},{"v":15.58},null]},{"c":[{"v":"Date(2012,8,26,2,11,15)"},{"v":18.2},{"v":18.0},null,{"v":15.34},{"v":15.91},null]},{"c":[{"v":"Date(2012,8,26,2,13,23)"},{"v":18.19},{"v":18.0},null,{"v":15.5},{"v":16.12},null]},{"c":[{"v":"Date(2012,8,26,2,15,30)"},{"v":18.19},{"v":18.0},null,{"v":15.63},{"v":16.07},null]},{"c":[{"v":"Date(2012,8,26,2,17,37)"},{"v":18.19},{"v":18.0},null,{"v":15.8},{"v":15.87},null]},{"c":[{"v":"Date(2012,8,26,2,19,44)"},{"v":18.18},{"v":18.0},null,{"v":15.93},{"v":15.77},null]},{"c":[{"v":"Date(2012,8,26,2,21,52)"},{"v":18.18},{"v":18.0},null,{"v":16.06},{"v":15.74},null]},{"c":[{"v":"Date(2012,8,26,2,23,59)"},{"v":18.17},{"v":18.0},null,{"v":16.2},{"v":15.73},null]},{"c":[{"v":"Date(2012,8,26,2,26,6)"},{"v":18.16},{"v":18.0},null,{"v":16.18},{"v":16.1},null]},{"c":[{"v":"Date(2012,8,26,2,28,13)"},{"v":18.15},{"v":18.0},null,{"v":15.91},{"v":16.19},null]},{"c":[{"v":"Date(2012,8,26,2,30,21)"},{"v":18.14},{"v":18.0},null,{"v":15.69},{"v":16.56},null]},{"c":[{"v":"Date(2012,8,26,2,32,28)"},{"v":18.13},{"v":18.0},null,{"v":15.56},{"v":16.87},null]},{"c":[{"v":"Date(2012,8,26,2,34,35)"},{"v":18.13},{"v":18.0},null,{"v":15.5},{"v":16.82},null]},{"c":[{"v":"Date(2012,8,26,2,36,42)"},{"v":18.12},{"v":18.0},null,{"v":15.51},{"v":16.71},null]},{"c":[{"v":"Date(2012,8,26,2,38,49)"},{"v":18.12},{"v":18.0},null,{"v":15.56},{"v":16.66},null]},{"c":[{"v":"Date(2012,8,26,2,40,57)"},{"v":18.11},{"v":18.0},null,{"v":15.64},{"v":16.69},null]},{"c":[{"v":"Date(2012,8,26,2,43,4)"},{"v":18.09},{"v":18.0},null,{"v":15.75},{"v":17.08},null]},{"c":[{"v":"Date(2012,8,26,2,45,11)"},{"v":18.07},{"v":18.0},null,{"v":15.86},{"v":17.64},null]},{"c":[{"v":"Date(2012,8,26,2,47,18)"},{"v":18.06},{"v":18.0},null,{"v":15.96},{"v":17.88},null]},{"c":[{"v":"Date(2012,8,26,2,49,26)"},{"v":18.07},{"v":18.0},null,{"v":16.07},{"v":17.71},null]},{"c":[{"v":"Date(2012,8,26,2,51,33)"},{"v":18.06},{"v":18.0},null,{"v":16.19},{"v":17.69},null]},{"c":[{"v":"Date(2012,8,26,2,53,40)"},{"v":18.06},{"v":18.0},null,{"v":16.31},{"v":17.53},null]},{"c":[{"v":"Date(2012,8,26,2,55,47)"},{"v":18.06},{"v":18.0},null,{"v":16.43},{"v":17.41},null]},{"c":[{"v":"Date(2012,8,26,2,57,55)"},{"v":18.06},{"v":18.0},null,{"v":16.52},{"v":17.37},null]},{"c":[{"v":"Date(2012,8,26,3,0,2)"},{"v":18.06},{"v":18.0},null,{"v":16.62},{"v":17.28},null]},{"c":[{"v":"Date(2012,8,26,3,2,9)"},{"v":18.05},{"v":18.0},null,{"v":16.73},{"v":17.33},null]},{"c":[{"v":"Date(2012,8,26,3,4,16)"},{"v":18.04},{"v":18.0},null,{"v":16.81},{"v":17.46},null]},{"c":[{"v":"Date(2012,8,26,3,6,24)"},{"v":18.04},{"v":18.0},null,{"v":16.93},{"v":17.44},null]},{"c":[{"v":"Date(2012,8,26,3,8,31)"},{"v":18.03},{"v":18.0},null,{"v":17.0},{"v":17.67},null]},{"c":[{"v":"Date(2012,8,26,3,10,38)"},{"v":18.04},{"v":18.0},null,{"v":17.08},{"v":17.76},null]},{"c":[{"v":"Date(2012,8,26,3,12,46)"},{"v":18.02},{"v":18.0},null,{"v":17.18},{"v":17.92},null]},{"c":[{"v":"Date(2012,8,26,3,14,53)"},{"v":18.02},{"v":18.0},null,{"v":17.25},{"v":17.99},null]},{"c":[{"v":"Date(2012,8,26,3,17,0)"},{"v":18.02},{"v":18.0},null,{"v":17.31},{"v":18.02},null]},{"c":[{"v":"Date(2012,8,26,3,19,7)"},{"v":18.03},{"v":18.0},null,{"v":17.41},{"v":17.94},null]},{"c":[{"v":"Date(2012,8,26,3,21,15)"},{"v":18.01},{"v":18.0},null,{"v":17.49},{"v":18.1},null]},{"c":[{"v":"Date(2012,8,26,3,23,22)"},{"v":18.01},{"v":18.0},null,{"v":17.5},{"v":18.04},null]},{"c":[{"v":"Date(2012,8,26,3,25,29)"},{"v":18.01},{"v":18.0},null,{"v":17.56},{"v":18.12},null]},{"c":[{"v":"Date(2012,8,26,3,27,36)"},{"v":18.0},{"v":18.0},null,{"v":17.57},{"v":18.16},null]},{"c":[{"v":"Date(2012,8,26,3,29,44)"},{"v":18.0},{"v":18.0},null,{"v":17.63},{"v":18.2},null]},{"c":[{"v":"Date(2012,8,26,3,31,51)"},{"v":18.01},{"v":18.0},null,{"v":17.69},{"v":18.05},null]},{"c":[{"v":"Date(2012,8,26,3,33,58)"},{"v":18.01},{"v":18.0},null,{"v":17.75},{"v":17.98},null]},{"c":[{"v":"Date(2012,8,26,3,36,6)"},{"v":18.0},{"v":18.0},null,{"v":17.8},{"v":18.05},null]},{"c":[{"v":"Date(2012,8,26,3,38,13)"},{"v":18.0},{"v":18.0},null,{"v":17.84},{"v":18.09},null]},{"c":[{"v":"Date(2012,8,26,3,40,20)"},{"v":18.0},{"v":18.0},null,{"v":17.88},{"v":18.08},null]},{"c":[{"v":"Date(2012,8,26,3,42,27)"},{"v":18.0},{"v":18.0},null,{"v":17.94},{"v":18.02},null]},{"c":[{"v":"Date(2012,8,26,3,44,35)"},{"v":18.0},{"v":18.0},null,{"v":17.99},{"v":18.01},null]},{"c":[{"v":"Date(2012,8,26,3,46,42)"},{"v":18.0},{"v":18.0},null,{"v":18.0},{"v":18.02},null]},{"c":[{"v":"Date(2012,8,26,3,48,49)"},{"v":18.0},{"v":18.0},null,{"v":18.06},{"v":18.02},null]},{"c":[{"v":"Date(2012,8,26,3,50,57)"},{"v":18.0},{"v":18.0},null,{"v":18.08},{"v":18.01},null]},{"c":[{"v":"Date(2012,8,26,3,53,4)"},{"v":18.0},{"v":18.0},null,{"v":18.12},{"v":17.98},null]},{"c":[{"v":"Date(2012,8,26,3,55,11)"},{"v":18.0},{"v":18.0},null,{"v":18.16},{"v":17.94},null]},{"c":[{"v":"Date(2012,8,26,3,57,18)"},{"v":18.0},{"v":18.0},null,{"v":18.19},{"v":18.0},null]},{"c":[{"v":"Date(2012,8,26,3,59,26)"},{"v":18.0},{"v":18.0},null,{"v":18.19},{"v":17.94},null]},{"c":[{"v":"Date(2012,8,26,4,1,33)"},{"v":18.0},{"v":18.0},null,{"v":18.25},{"v":17.99},null]},{"c":[{"v":"Date(2012,8,26,4,3,40)"},{"v":18.0},{"v":18.0},null,{"v":18.25},{"v":17.94},null]},{"c":[{"v":"Date(2012,8,26,4,5,48)"},{"v":18.0},{"v":18.0},null,{"v":18.3},{"v":17.98},null]},{"c":[{"v":"Date(2012,8,26,4,7,55)"},{"v":18.0},{"v":18.0},null,{"v":18.31},{"v":17.98},null]},{"c":[{"v":"Date(2012,8,26,4,10,2)"},{"v":18.0},{"v":18.0},null,{"v":18.31},{"v":17.99},null]},{"c":[{"v":"Date(2012,8,26,4,12,10)"},{"v":18.0},{"v":18.0},{"v":"Beer temperature setting changed to  19.00 by profile temperature profile."},{"v":18.37},{"v":17.99},null]},{"c":[{"v":"Date(2012,8,26,4,12,11)"},{"v":18.0},{"v":19.0},null,{"v":18.37},{"v":30.0},null]},{"c":[{"v":"Date(2012,8,26,4,14,19)"},{"v":18.0},{"v":19.0},null,{"v":18.49},{"v":30.0},null]},{"c":[{"v":"Date(2012,8,26,4,16,26)"},{"v":18.0},{"v":19.0},null,{"v":18.63},{"v":30.0},null]},{"c":[{"v":"Date(2012,8,26,4,18,33)"},{"v":18.01},{"v":19.0},null,{"v":18.75},{"v":30.0},null]},{"c":[{"v":"Date(2012,8,26,4,20,41)"},{"v":18.0},{"v":19.0},null,{"v":18.88},{"v":30.0},null]},{"c":[{"v":"Date(2012,8,26,4,22,48)"},{"v":18.01},{"v":19.0},null,{"v":19.0},{"v":30.0},null]},{"c":[{"v":"Date(2012,8,26,4,24,55)"},{"v":18.02},{"v":19.0},null,{"v":19.12},{"v":30.0},null]},{"c":[{"v":"Date(2012,8,26,4,27,3)"},{"v":18.02},{"v":19.0},null,{"v":19.19},{"v":30.0},null]},{"c":[{"v":"Date(2012,8,26,4,29,10)"},{"v":18.03},{"v":19.0},null,{"v":19.31},{"v":30.0},null]},{"c":[{"v":"Date(2012,8,26,4,31,17)"},{"v":18.04},{"v":19.0},null,{"v":19.38},{"v":30.0},null]},{"c":[{"v":"Date(2012,8,26,4,33,25)"},{"v":18.04},{"v":19.0},null,{"v":19.46},{"v":30.0},null]},{"c":[{"v":"Date(2012,8,26,4,35,32)"},{"v":18.04},{"v":19.0},null,{"v":19.55},{"v":30.0},null]},{"c":[{"v":"Date(2012,8,26,4,37,39)"},{"v":18.05},{"v":19.0},null,{"v":19.62},{"v":30.0},null]},{"c":[{"v":"Date(2012,8,26,4,39,47)"},{"v":18.06},{"v":19.0},null,{"v":19.69},{"v":30.0},null]},{"c":[{"v":"Date(2012,8,26,4,41,54)"},{"v":18.06},{"v":19.0},null,{"v":19.78},{"v":30.0},null]},{"c":[{"v":"Date(2012,8,26,4,44,2)"},{"v":18.06},{"v":19.0},null,{"v":19.85},{"v":30.0},null]},{"c":[{"v":"Date(2012,8,26,4,46,9)"},{"v":18.06},{"v":19.0},null,{"v":19.93},{"v":30.0},null]},{"c":[{"v":"Date(2012,8,26,4,48,16)"},{"v":18.06},{"v":19.0},null,{"v":20.0},{"v":30.0},null]},{"c":[{"v":"Date(2012,8,26,4,50,24)"},{"v":18.06},{"v":19.0},null,{"v":20.06},{"v":30.0},null]},{"c":[{"v":"Date(2012,8,26,4,52,31)"},{"v":18.06},{"v":19.0},null,{"v":20.12},{"v":30.0},null]},{"c":[{"v":"Date(2012,8,26,4,54,39)"},{"v":18.06},{"v":19.0},null,{"v":20.14},{"v":30.0},null]},{"c":[{"v":"Date(2012,8,26,4,56,46)"},{"v":18.07},{"v":19.0},null,{"v":20.19},{"v":30.0},null]},{"c":[{"v":"Date(2012,8,26,4,58,53)"},{"v":18.06},{"v":19.0},null,{"v":20.25},{"v":30.0},null]},{"c":[{"v":"Date(2012,8,26,5,1,1)"},{"v":18.07},{"v":19.0},null,{"v":20.3},{"v":30.0},null]},{"c":[{"v":"Date(2012,8,26,5,3,8)"},{"v":18.08},{"v":19.0},null,{"v":20.33},{"v":30.0},null]},{"c":[{"v":"Date(2012,8,26,5,5,15)"},{"v":18.1},{"v":19.0},null,{"v":20.38},{"v":30.0},null]},{"c":[{"v":"Date(2012,8,26,5,7,23)"},{"v":18.1},{"v":19.0},null,{"v":20.43},{"v":30.0},null]},{"c":[{"v":"Date(2012,8,26,5,9,30)"},{"v":18.11},{"v":19.0},null,{"v":20.45},{"v":30.0},null]},{"c":[{"v":"Date(2012,8,26,5,11,38)"},{"v":18.12},{"v":19.0},null,{"v":20.5},{"v":30.0},null]},{"c":[{"v":"Date(2012,8,26,5,13,45)"},{"v":18.12},{"v":19.0},null,{"v":20.53},{"v":30.0},null]},{"c":[{"v":"Date(2012,8,26,5,15,52)"},{"v":18.12},{"v":19.0},null,{"v":20.56},{"v":30.0},null]},{"c":[{"v":"Date(2012,8,26,5,18,0)"},{"v":18.13},{"v":19.0},null,{"v":20.58},{"v":30.0},null]},{"c":[{"v":"Date(2012,8,26,5,20,7)"},{"v":18.13},{"v":19.0},null,{"v":20.62},{"v":30.0},null]},{"c":[{"v":"Date(2012,8,26,5,22,14)"},{"v":18.13},{"v":19.0},null,{"v":20.63},{"v":30.0},null]},{"c":[{"v":"Date(2012,8,26,5,24,22)"},{"v":18.14},{"v":19.0},null,{"v":20.68},{"v":30.0},null]},{"c":[{"v":"Date(2012,8,26,5,26,29)"},{"v":18.13},{"v":19.0},null,{"v":20.69},{"v":30.0},null]},{"c":[{"v":"Date(2012,8,26,5,28,37)"},{"v":18.15},{"v":19.0},null,{"v":20.7},{"v":30.0},null]},{"c":[{"v":"Date(2012,8,26,5,30,44)"},{"v":18.14},{"v":19.0},null,{"v":20.75},{"v":30.0},null]},{"c":[{"v":"Date(2012,8,26,5,32,51)"},{"v":18.17},{"v":19.0},null,{"v":20.75},{"v":30.0},null]},{"c":[{"v":"Date(2012,8,26,5,34,59)"},{"v":18.18},{"v":19.0},null,{"v":20.78},{"v":30.0},null]},{"c":[{"v":"Date(2012,8,26,5,37,6)"},{"v":18.18},{"v":19.0},null,{"v":20.81},{"v":30.0},null]},{"c":[{"v":"Date(2012,8,26,5,39,14)"},{"v":18.19},{"v":19.0},null,{"v":20.81},{"v":30.0},null]},{"c":[{"v":"Date(2012,8,26,5,41,21)"},{"v":18.19},{"v":19.0},null,{"v":20.83},{"v":30.0},null]},{"c":[{"v":"Date(2012,8,26,5,43,29)"},{"v":18.19},{"v":19.0},null,{"v":20.87},{"v":30.0},null]},{"c":[{"v":"Date(2012,8,26,5,45,36)"},{"v":18.19},{"v":19.0},null,{"v":20.88},{"v":30.0},null]},{"c":[{"v":"Date(2012,8,26,5,47,43)"},{"v":18.19},{"v":19.0},null,{"v":20.89},{"v":30.0},null]},{"c":[{"v":"Date(2012,8,26,5,49,51)"},{"v":18.19},{"v":19.0},null,{"v":20.93},{"v":30.0},null]},{"c":[{"v":"Date(2012,8,26,5,51,58)"},{"v":18.19},{"v":19.0},null,{"v":20.94},{"v":30.0},null]},{"c":[{"v":"Date(2012,8,26,5,54,6)"},{"v":18.22},{"v":19.0},null,{"v":20.94},{"v":30.0},null]},{"c":[{"v":"Date(2012,8,26,5,56,13)"},{"v":18.22},{"v":19.0},null,{"v":20.95},{"v":30.0},null]},{"c":[{"v":"Date(2012,8,26,5,58,21)"},{"v":18.23},{"v":19.0},null,{"v":21.0},{"v":30.0},null]},{"c":[{"v":"Date(2012,8,26,6,0,28)"},{"v":18.24},{"v":19.0},null,{"v":21.0},{"v":29.81},null]},{"c":[{"v":"Date(2012,8,26,6,2,35)"},{"v":18.24},{"v":19.0},null,{"v":21.0},{"v":29.71},null]},{"c":[{"v":"Date(2012,8,26,6,4,43)"},{"v":18.25},{"v":19.0},null,{"v":21.01},{"v":29.75},null]},{"c":[{"v":"Date(2012,8,26,6,6,50)"},{"v":18.25},{"v":19.0},null,{"v":21.05},{"v":29.81},null]},{"c":[{"v":"Date(2012,8,26,6,8,58)"},{"v":18.25},{"v":19.0},null,{"v":21.06},{"v":29.92},null]},{"c":[{"v":"Date(2012,8,26,6,11,5)"},{"v":18.25},{"v":19.0},null,{"v":21.06},{"v":30.0},null]},{"c":[{"v":"Date(2012,8,26,6,13,13)"},{"v":18.26},{"v":19.0},null,{"v":21.06},{"v":29.86},null]},{"c":[{"v":"Date(2012,8,26,6,15,20)"},{"v":18.26},{"v":19.0},null,{"v":21.08},{"v":29.85},null]},{"c":[{"v":"Date(2012,8,26,6,17,27)"},{"v":18.28},{"v":19.0},null,{"v":21.12},{"v":29.52},null]},{"c":[{"v":"Date(2012,8,26,6,19,35)"},{"v":18.29},{"v":19.0},null,{"v":21.12},{"v":29.26},null]},{"c":[{"v":"Date(2012,8,26,6,21,42)"},{"v":18.3},{"v":19.0},null,{"v":21.12},{"v":28.98},null]},{"c":[{"v":"Date(2012,8,26,6,23,50)"},{"v":18.3},{"v":19.0},null,{"v":21.13},{"v":28.8},null]},{"c":[{"v":"Date(2012,8,26,6,25,57)"},{"v":18.31},{"v":19.0},null,{"v":21.13},{"v":28.74},null]},{"c":[{"v":"Date(2012,8,26,6,28,5)"},{"v":18.31},{"v":19.0},null,{"v":21.16},{"v":28.78},null]},{"c":[{"v":"Date(2012,8,26,6,30,12)"},{"v":18.31},{"v":19.0},null,{"v":21.18},{"v":28.92},null]},{"c":[{"v":"Date(2012,8,26,6,32,19)"},{"v":18.31},{"v":19.0},null,{"v":21.19},{"v":29.02},null]},{"c":[{"v":"Date(2012,8,26,6,34,27)"},{"v":18.31},{"v":19.0},null,{"v":21.19},{"v":29.07},null]},{"c":[{"v":"Date(2012,8,26,6,36,34)"},{"v":18.32},{"v":19.0},null,{"v":21.19},{"v":28.96},null]},{"c":[{"v":"Date(2012,8,26,6,38,42)"},{"v":18.33},{"v":19.0},null,{"v":21.19},{"v":28.87},null]},{"c":[{"v":"Date(2012,8,26,6,40,49)"},{"v":18.34},{"v":19.0},null,{"v":21.21},{"v":28.63},null]},{"c":[{"v":"Date(2012,8,26,6,42,57)"},{"v":18.34},{"v":19.0},null,{"v":21.23},{"v":28.41},null]},{"c":[{"v":"Date(2012,8,26,6,45,4)"},{"v":18.37},{"v":19.0},null,{"v":21.25},{"v":27.92},null]},{"c":[{"v":"Date(2012,8,26,6,47,12)"},{"v":18.37},{"v":19.0},null,{"v":21.25},{"v":27.8},null]},{"c":[{"v":"Date(2012,8,26,6,49,19)"},{"v":18.37},{"v":19.0},null,{"v":21.25},{"v":27.77},null]},{"c":[{"v":"Date(2012,8,26,6,51,27)"},{"v":18.37},{"v":19.0},null,{"v":21.25},{"v":27.92},null]},{"c":[{"v":"Date(2012,8,26,6,53,34)"},{"v":18.38},{"v":19.0},null,{"v":21.26},{"v":27.99},null]},{"c":[{"v":"Date(2012,8,26,6,55,41)"},{"v":18.38},{"v":19.0},null,{"v":21.28},{"v":28.01},null]},{"c":[{"v":"Date(2012,8,26,6,57,49)"},{"v":18.38},{"v":19.0},null,{"v":21.31},{"v":27.99},null]},{"c":[{"v":"Date(2012,8,26,6,59,56)"},{"v":18.39},{"v":19.0},null,{"v":21.31},{"v":27.71},null]},{"c":[{"v":"Date(2012,8,26,7,2,4)"},{"v":18.41},{"v":19.0},null,{"v":21.31},{"v":27.52},null]},{"c":[{"v":"Date(2012,8,26,7,4,11)"},{"v":18.42},{"v":19.0},null,{"v":21.31},{"v":27.22},null]},{"c":[{"v":"Date(2012,8,26,7,6,19)"},{"v":18.43},{"v":19.0},null,{"v":21.31},{"v":26.86},null]},{"c":[{"v":"Date(2012,8,26,7,8,26)"},{"v":18.44},{"v":19.0},null,{"v":21.32},{"v":26.8},null]},{"c":[{"v":"Date(2012,8,26,7,10,34)"},{"v":18.44},{"v":19.0},null,{"v":21.33},{"v":26.85},null]},{"c":[{"v":"Date(2012,8,26,7,12,41)"},{"v":18.44},{"v":19.0},null,{"v":21.36},{"v":26.97},null]},{"c":[{"v":"Date(2012,8,26,7,14,49)"},{"v":18.44},{"v":19.0},null,{"v":21.37},{"v":27.09},null]},{"c":[{"v":"Date(2012,8,26,7,16,56)"},{"v":18.44},{"v":19.0},null,{"v":21.37},{"v":27.16},null]},{"c":[{"v":"Date(2012,8,26,7,19,4)"},{"v":18.45},{"v":19.0},null,{"v":21.38},{"v":26.99},null]},{"c":[{"v":"Date(2012,8,26,7,21,11)"},{"v":18.46},{"v":19.0},null,{"v":21.38},{"v":26.67},null]},{"c":[{"v":"Date(2012,8,26,7,23,18)"},{"v":18.47},{"v":19.0},null,{"v":21.38},{"v":26.47},null]},{"c":[{"v":"Date(2012,8,26,7,25,26)"},{"v":18.48},{"v":19.0},null,{"v":21.38},{"v":26.21},null]},{"c":[{"v":"Date(2012,8,26,7,27,34)"},{"v":18.5},{"v":19.0},null,{"v":21.4},{"v":25.87},null]},{"c":[{"v":"Date(2012,8,26,7,29,41)"},{"v":18.5},{"v":19.0},null,{"v":21.42},{"v":25.88},null]},{"c":[{"v":"Date(2012,8,26,7,31,48)"},{"v":18.5},{"v":19.0},null,{"v":21.43},{"v":25.98},null]},{"c":[{"v":"Date(2012,8,26,7,33,56)"},{"v":18.5},{"v":19.0},null,{"v":21.44},{"v":26.06},null]},{"c":[{"v":"Date(2012,8,26,7,36,3)"},{"v":18.51},{"v":19.0},null,{"v":21.44},{"v":26.09},null]},{"c":[{"v":"Date(2012,8,26,7,38,11)"},{"v":18.51},{"v":19.0},null,{"v":21.44},{"v":26.0},null]},{"c":[{"v":"Date(2012,8,26,7,40,18)"},{"v":18.53},{"v":19.0},null,{"v":21.44},{"v":25.75},null]},{"c":[{"v":"Date(2012,8,26,7,42,26)"},{"v":18.53},{"v":19.0},null,{"v":21.44},{"v":25.61},null]},{"c":[{"v":"Date(2012,8,26,7,44,33)"},{"v":18.54},{"v":19.0},null,{"v":21.46},{"v":25.23},null]},{"c":[{"v":"Date(2012,8,26,7,46,41)"},{"v":18.55},{"v":19.0},null,{"v":21.46},{"v":25.09},null]},{"c":[{"v":"Date(2012,8,26,7,48,48)"},{"v":18.56},{"v":19.0},null,{"v":21.49},{"v":24.93},null]},{"c":[{"v":"Date(2012,8,26,7,50,56)"},{"v":18.56},{"v":19.0},null,{"v":21.5},{"v":24.97},null]},{"c":[{"v":"Date(2012,8,26,7,53,3)"},{"v":18.56},{"v":19.0},null,{"v":21.5},{"v":25.08},null]},{"c":[{"v":"Date(2012,8,26,7,55,11)"},{"v":18.56},{"v":19.0},null,{"v":21.5},{"v":25.23},null]},{"c":[{"v":"Date(2012,8,26,7,57,18)"},{"v":18.56},{"v":19.0},null,{"v":21.5},{"v":25.27},null]},{"c":[{"v":"Date(2012,8,26,7,59,26)"},{"v":18.57},{"v":19.0},null,{"v":21.53},{"v":25.2},null]},{"c":[{"v":"Date(2012,8,26,8,1,33)"},{"v":18.59},{"v":19.0},null,{"v":21.55},{"v":24.87},null]},{"c":[{"v":"Date(2012,8,26,8,3,41)"},{"v":18.6},{"v":19.0},null,{"v":21.56},{"v":24.54},null]},{"c":[{"v":"Date(2012,8,26,8,5,49)"},{"v":18.62},{"v":19.0},null,{"v":21.56},{"v":24.02},null]},{"c":[{"v":"Date(2012,8,26,8,7,56)"},{"v":18.61},{"v":19.0},null,{"v":21.56},{"v":24.16},null]},{"c":[{"v":"Date(2012,8,26,8,10,4)"},{"v":18.62},{"v":19.0},null,{"v":21.56},{"v":24.04},null]},{"c":[{"v":"Date(2012,8,26,8,12,11)"},{"v":18.63},{"v":19.0},null,{"v":21.57},{"v":24.11},null]},{"c":[{"v":"Date(2012,8,26,8,14,19)"},{"v":18.63},{"v":19.0},null,{"v":21.58},{"v":24.22},null]},{"c":[{"v":"Date(2012,8,26,8,16,26)"},{"v":18.63},{"v":19.0},null,{"v":21.61},{"v":24.15},null]},{"c":[{"v":"Date(2012,8,26,8,18,34)"},{"v":18.63},{"v":19.0},null,{"v":21.62},{"v":24.21},null]},{"c":[{"v":"Date(2012,8,26,8,20,41)"},{"v":18.66},{"v":19.0},null,{"v":21.63},{"v":23.67},null]},{"c":[{"v":"Date(2012,8,26,8,22,49)"},{"v":18.67},{"v":19.0},null,{"v":21.63},{"v":23.44},null]},{"c":[{"v":"Date(2012,8,26,8,24,56)"},{"v":18.68},{"v":19.0},null,{"v":21.63},{"v":23.24},null]},{"c":[{"v":"Date(2012,8,26,8,27,4)"},{"v":18.68},{"v":19.0},null,{"v":21.63},{"v":23.09},null]},{"c":[{"v":"Date(2012,8,26,8,29,11)"},{"v":18.69},{"v":19.0},null,{"v":21.64},{"v":23.07},null]},{"c":[{"v":"Date(2012,8,26,8,31,19)"},{"v":18.69},{"v":19.0},null,{"v":21.67},{"v":23.21},null]},{"c":[{"v":"Date(2012,8,26,8,33,26)"},{"v":18.69},{"v":19.0},null,{"v":21.68},{"v":23.28},null]},{"c":[{"v":"Date(2012,8,26,8,35,34)"},{"v":18.69},{"v":19.0},null,{"v":21.69},{"v":23.36},null]},{"c":[{"v":"Date(2012,8,26,8,37,41)"},{"v":18.7},{"v":19.0},null,{"v":21.69},{"v":23.29},null]},{"c":[{"v":"Date(2012,8,26,8,39,49)"},{"v":18.7},{"v":19.0},null,{"v":21.69},{"v":23.17},null]},{"c":[{"v":"Date(2012,8,26,8,41,57)"},{"v":18.72},{"v":19.0},null,{"v":21.69},{"v":22.68},null]},{"c":[{"v":"Date(2012,8,26,8,44,4)"},{"v":18.74},{"v":19.0},null,{"v":21.7},{"v":22.3},null]},{"c":[{"v":"Date(2012,8,26,8,46,12)"},{"v":18.74},{"v":19.0},null,{"v":21.72},{"v":22.17},null]},{"c":[{"v":"Date(2012,8,26,8,48,19)"},{"v":18.75},{"v":19.0},null,{"v":21.74},{"v":22.11},null]},{"c":[{"v":"Date(2012,8,26,8,50,27)"},{"v":18.75},{"v":19.0},null,{"v":21.75},{"v":22.22},null]},{"c":[{"v":"Date(2012,8,26,8,52,34)"},{"v":18.75},{"v":19.0},null,{"v":21.75},{"v":22.31},null]},{"c":[{"v":"Date(2012,8,26,8,54,42)"},{"v":18.75},{"v":19.0},null,{"v":21.76},{"v":22.4},null]},{"c":[{"v":"Date(2012,8,26,8,56,49)"},{"v":18.76},{"v":19.0},null,{"v":21.78},{"v":22.34},null]},{"c":[{"v":"Date(2012,8,26,8,58,57)"},{"v":18.78},{"v":19.0},null,{"v":21.8},{"v":21.89},null]},{"c":[{"v":"Date(2012,8,26,9,1,4)"},{"v":18.79},{"v":19.0},null,{"v":21.71},{"v":21.45},null]},{"c":[{"v":"Date(2012,8,26,9,3,12)"},{"v":18.8},{"v":19.0},null,{"v":21.63},{"v":21.33},null]},{"c":[{"v":"Date(2012,8,26,9,5,20)"},{"v":18.81},{"v":19.0},null,{"v":21.55},{"v":21.22},null]},{"c":[{"v":"Date(2012,8,26,9,7,27)"},{"v":18.81},{"v":19.0},null,{"v":21.46},{"v":21.23},null]},{"c":[{"v":"Date(2012,8,26,9,9,35)"},{"v":18.81},{"v":19.0},null,{"v":21.38},{"v":21.3},null]},{"c":[{"v":"Date(2012,8,26,9,11,42)"},{"v":18.81},{"v":19.0},null,{"v":21.31},{"v":21.41},null]},{"c":[{"v":"Date(2012,8,26,9,13,50)"},{"v":18.81},{"v":19.0},null,{"v":21.25},{"v":21.52},null]},{"c":[{"v":"Date(2012,8,26,9,15,59)"},{"v":18.82},{"v":18.9},null,{"v":21.19},{"v":19.96},null]},{"c":[{"v":"Date(2012,8,26,9,18,6)"},{"v":18.82},{"v":18.9},null,{"v":21.13},{"v":19.85},null]},{"c":[{"v":"Date(2012,8,26,9,20,14)"},{"v":18.83},{"v":18.9},null,{"v":21.06},{"v":19.62},null]},{"c":[{"v":"Date(2012,8,26,9,22,21)"},{"v":18.84},{"v":18.9},null,{"v":21.02},{"v":19.38},null]},{"c":[{"v":"Date(2012,8,26,9,24,29)"},{"v":18.86},{"v":18.9},null,{"v":20.99},{"v":19.01},null]},{"c":[{"v":"Date(2012,8,26,9,26,37)"},{"v":18.86},{"v":18.9},null,{"v":20.94},{"v":18.88},null]},{"c":[{"v":"Date(2012,8,26,9,28,44)"},{"v":18.87},{"v":18.9},null,{"v":20.88},{"v":18.85},null]},{"c":[{"v":"Date(2012,8,26,9,30,52)"},{"v":18.87},{"v":18.9},null,{"v":20.84},{"v":18.79},null]},{"c":[{"v":"Date(2012,8,26,9,32,59)"},{"v":18.87},{"v":18.9},null,{"v":20.81},{"v":18.85},null]},{"c":[{"v":"Date(2012,8,26,9,35,7)"},{"v":18.88},{"v":18.9},null,{"v":20.75},{"v":18.93},null]},{"c":[{"v":"Date(2012,8,26,9,37,14)"},{"v":18.88},{"v":18.9},null,{"v":20.73},{"v":19.02},null]},{"c":[{"v":"Date(2012,8,26,9,39,22)"},{"v":18.88},{"v":18.9},null,{"v":20.69},{"v":19.05},null]},{"c":[{"v":"Date(2012,8,26,9,41,30)"},{"v":18.88},{"v":18.9},null,{"v":20.65},{"v":19.11},null]},{"c":[{"v":"Date(2012,8,26,9,43,34)"},{"v":18.88},{"v":18.8},null,{"v":20.63},{"v":17.46},null]},{"c":[{"v":"Date(2012,8,26,9,45,42)"},{"v":18.88},{"v":18.8},null,{"v":20.57},{"v":17.37},null]},{"c":[{"v":"Date(2012,8,26,9,47,49)"},{"v":18.9},{"v":18.8},null,{"v":20.52},{"v":17.06},null]},{"c":[{"v":"Date(2012,8,26,9,49,57)"},{"v":18.9},{"v":18.8},null,{"v":20.38},{"v":17.02},null]},{"c":[{"v":"Date(2012,8,26,9,52,5)"},{"v":18.89},{"v":18.8},null,{"v":20.01},{"v":17.2},null]},{"c":[{"v":"Date(2012,8,26,9,54,12)"},{"v":18.88},{"v":18.8},null,{"v":19.41},{"v":17.42},null]},{"c":[{"v":"Date(2012,8,26,9,56,20)"},{"v":18.88},{"v":18.8},null,{"v":18.6},{"v":17.7},null]},{"c":[{"v":"Date(2012,8,26,9,58,28)"},{"v":18.88},{"v":18.8},null,{"v":17.81},{"v":17.75},null]},{"c":[{"v":"Date(2012,8,26,10,0,35)"},{"v":18.87},{"v":18.8},null,{"v":17.32},{"v":17.81},null]},{"c":[{"v":"Date(2012,8,26,10,2,43)"},{"v":18.86},{"v":18.8},null,{"v":17.07},{"v":18.06},null]},{"c":[{"v":"Date(2012,8,26,10,4,50)"},{"v":18.85},{"v":18.8},null,{"v":16.94},{"v":18.38},null]},{"c":[{"v":"Date(2012,8,26,10,6,58)"},{"v":18.82},{"v":18.8},null,{"v":16.88},{"v":18.95},null]},{"c":[{"v":"Date(2012,8,26,10,9,6)"},{"v":18.82},{"v":18.8},null,{"v":16.92},{"v":19.18},null]},{"c":[{"v":"Date(2012,8,26,10,11,13)"},{"v":18.82},{"v":18.8},null,{"v":16.95},{"v":19.12},null]},{"c":[{"v":"Date(2012,8,26,10,13,22)"},{"v":18.81},{"v":18.7},null,{"v":17.04},{"v":17.54},null]},{"c":[{"v":"Date(2012,8,26,10,15,30)"},{"v":18.81},{"v":18.7},null,{"v":17.12},{"v":17.44},null]},{"c":[{"v":"Date(2012,8,26,10,17,40)"},{"v":18.81},{"v":18.7},null,{"v":17.24},{"v":17.34},null]},{"c":[{"v":"Date(2012,8,26,10,19,48)"},{"v":18.81},{"v":18.7},null,{"v":17.31},{"v":17.25},null]},{"c":[{"v":"Date(2012,8,26,10,21,55)"},{"v":18.81},{"v":18.7},null,{"v":17.44},{"v":17.12},null]},{"c":[{"v":"Date(2012,8,26,10,24,3)"},{"v":18.81},{"v":18.7},null,{"v":17.56},{"v":16.99},null]},{"c":[{"v":"Date(2012,8,26,10,26,10)"},{"v":18.81},{"v":18.7},null,{"v":17.62},{"v":16.88},null]},{"c":[{"v":"Date(2012,8,26,10,28,18)"},{"v":18.81},{"v":18.7},null,{"v":17.5},{"v":16.8},null]},{"c":[{"v":"Date(2012,8,26,10,30,26)"},{"v":18.81},{"v":18.7},null,{"v":17.13},{"v":16.77},null]},{"c":[{"v":"Date(2012,8,26,10,32,33)"},{"v":18.8},{"v":18.7},null,{"v":16.72},{"v":16.87},null]},{"c":[{"v":"Date(2012,8,26,10,34,41)"},{"v":18.79},{"v":18.7},null,{"v":16.46},{"v":16.96},null]},{"c":[{"v":"Date(2012,8,26,10,36,49)"},{"v":18.78},{"v":18.7},null,{"v":16.32},{"v":17.39},null]},{"c":[{"v":"Date(2012,8,26,10,38,56)"},{"v":18.77},{"v":18.7},null,{"v":16.29},{"v":17.87},null]},{"c":[{"v":"Date(2012,8,26,10,41,5)"},{"v":18.76},{"v":18.6},null,{"v":16.31},{"v":16.58},null]},{"c":[{"v":"Date(2012,8,26,10,43,13)"},{"v":18.75},{"v":18.6},null,{"v":16.37},{"v":16.79},null]},{"c":[{"v":"Date(2012,8,26,10,45,20)"},{"v":18.75},{"v":18.6},null,{"v":16.49},{"v":16.77},null]},{"c":[{"v":"Date(2012,8,26,10,47,28)"},{"v":18.75},{"v":18.6},null,{"v":16.58},{"v":16.69},null]},{"c":[{"v":"Date(2012,8,26,10,49,32)"},{"v":18.75},{"v":18.6},null,{"v":16.71},{"v":16.61},null]},{"c":[{"v":"Date(2012,8,26,10,51,39)"},{"v":18.75},{"v":18.6},null,{"v":16.87},{"v":16.62},null]},{"c":[{"v":"Date(2012,8,26,10,53,47)"},{"v":18.75},{"v":18.6},null,{"v":17.0},{"v":16.46},null]},{"c":[{"v":"Date(2012,8,26,10,55,55)"},{"v":18.75},{"v":18.6},null,{"v":17.11},{"v":16.35},null]},{"c":[{"v":"Date(2012,8,26,10,58,2)"},{"v":18.74},{"v":18.6},null,{"v":17.0},{"v":16.37},null]},{"c":[{"v":"Date(2012,8,26,11,0,10)"},{"v":18.73},{"v":18.6},null,{"v":16.7},{"v":16.47},null]},{"c":[{"v":"Date(2012,8,26,11,2,18)"},{"v":18.72},{"v":18.6},null,{"v":16.36},{"v":16.77},null]},{"c":[{"v":"Date(2012,8,26,11,4,25)"},{"v":18.71},{"v":18.6},null,{"v":16.14},{"v":17.09},null]},{"c":[{"v":"Date(2012,8,26,11,6,33)"},{"v":18.69},{"v":18.6},null,{"v":16.06},{"v":17.63},null]},{"c":[{"v":"Date(2012,8,26,11,8,41)"},{"v":18.69},{"v":18.6},null,{"v":16.02},{"v":17.71},null]},{"c":[{"v":"Date(2012,8,26,11,10,50)"},{"v":18.69},{"v":18.5},null,{"v":16.06},{"v":16.14},null]},{"c":[{"v":"Date(2012,8,26,11,12,57)"},{"v":18.69},{"v":18.5},null,{"v":16.13},{"v":16.07},null]},{"c":[{"v":"Date(2012,8,26,11,15,5)"},{"v":18.69},{"v":18.5},null,{"v":16.26},{"v":15.96},null]},{"c":[{"v":"Date(2012,8,26,11,17,13)"},{"v":18.69},{"v":18.5},null,{"v":16.38},{"v":15.92},null]},{"c":[{"v":"Date(2012,8,26,11,19,20)"},{"v":18.68},{"v":18.5},null,{"v":16.5},{"v":15.87},null]},{"c":[{"v":"Date(2012,8,26,11,21,28)"},{"v":18.67},{"v":18.5},null,{"v":16.38},{"v":15.92},null]},{"c":[{"v":"Date(2012,8,26,11,23,36)"},{"v":18.66},{"v":18.5},null,{"v":16.05},{"v":16.23},null]},{"c":[{"v":"Date(2012,8,26,11,25,43)"},{"v":18.64},{"v":18.5},null,{"v":15.82},{"v":16.65},null]},{"c":[{"v":"Date(2012,8,26,11,27,51)"},{"v":18.63},{"v":18.5},null,{"v":15.69},{"v":16.88},null]},{"c":[{"v":"Date(2012,8,26,11,29,59)"},{"v":18.63},{"v":18.5},null,{"v":15.69},{"v":17.19},null]},{"c":[{"v":"Date(2012,8,26,11,32,7)"},{"v":18.63},{"v":18.5},null,{"v":15.74},{"v":17.21},null]},{"c":[{"v":"Date(2012,8,26,11,34,14)"},{"v":18.63},{"v":18.5},null,{"v":15.81},{"v":17.12},null]},{"c":[{"v":"Date(2012,8,26,11,36,18)"},{"v":18.62},{"v":18.5},null,{"v":15.94},{"v":17.08},null]},{"c":[{"v":"Date(2012,8,26,11,38,26)"},{"v":18.62},{"v":18.5},null,{"v":16.06},{"v":16.96},null]},{"c":[{"v":"Date(2012,8,26,11,40,35)"},{"v":18.61},{"v":18.4},null,{"v":16.16},{"v":15.51},null]},{"c":[{"v":"Date(2012,8,26,11,42,43)"},{"v":18.6},{"v":18.4},null,{"v":16.01},{"v":15.81},null]},{"c":[{"v":"Date(2012,8,26,11,44,50)"},{"v":18.58},{"v":18.4},null,{"v":15.77},{"v":16.15},null]},{"c":[{"v":"Date(2012,8,26,11,46,58)"},{"v":18.57},{"v":18.4},null,{"v":15.62},{"v":16.5},null]},{"c":[{"v":"Date(2012,8,26,11,49,6)"},{"v":18.57},{"v":18.4},null,{"v":15.57},{"v":16.55},null]},{"c":[{"v":"Date(2012,8,26,11,51,13)"},{"v":18.56},{"v":18.4},null,{"v":15.62},{"v":16.6},null]},{"c":[{"v":"Date(2012,8,26,11,53,21)"},{"v":18.56},{"v":18.4},null,{"v":15.71},{"v":16.56},null]},{"c":[{"v":"Date(2012,8,26,11,55,29)"},{"v":18.56},{"v":18.4},null,{"v":15.81},{"v":16.47},null]},{"c":[{"v":"Date(2012,8,26,11,57,37)"},{"v":18.56},{"v":18.4},null,{"v":15.95},{"v":16.35},null]},{"c":[{"v":"Date(2012,8,26,11,59,44)"},{"v":18.56},{"v":18.4},null,{"v":16.12},{"v":16.32},null]},{"c":[{"v":"Date(2012,8,26,12,1,52)"},{"v":18.54},{"v":18.4},null,{"v":16.28},{"v":16.47},null]},{"c":[{"v":"Date(2012,8,26,12,4,0)"},{"v":18.53},{"v":18.4},null,{"v":16.43},{"v":16.71},null]},{"c":[{"v":"Date(2012,8,26,12,6,7)"},{"v":18.53},{"v":18.4},null,{"v":16.59},{"v":16.93},null]},{"c":[{"v":"Date(2012,8,26,12,8,16)"},{"v":18.51},{"v":18.3},null,{"v":16.75},{"v":15.71},null]},{"c":[{"v":"Date(2012,8,26,12,10,24)"},{"v":18.51},{"v":18.3},null,{"v":16.81},{"v":15.8},null]},{"c":[{"v":"Date(2012,8,26,12,12,32)"},{"v":18.5},{"v":18.3},null,{"v":16.63},{"v":15.77},null]},{"c":[{"v":"Date(2012,8,26,12,14,40)"},{"v":18.51},{"v":18.3},null,{"v":16.28},{"v":15.64},null]},{"c":[{"v":"Date(2012,8,26,12,16,47)"},{"v":18.5},{"v":18.3},null,{"v":15.94},{"v":15.67},null]},{"c":[{"v":"Date(2012,8,26,12,18,55)"},{"v":18.5},{"v":18.3},null,{"v":15.74},{"v":15.64},null]},{"c":[{"v":"Date(2012,8,26,12,21,3)"},{"v":18.5},{"v":18.3},null,{"v":15.63},{"v":15.58},null]},{"c":[{"v":"Date(2012,8,26,12,23,10)"},{"v":18.49},{"v":18.3},null,{"v":15.62},{"v":15.7},null]},{"c":[{"v":"Date(2012,8,26,12,25,18)"},{"v":18.48},{"v":18.3},null,{"v":15.68},{"v":15.93},null]},{"c":[{"v":"Date(2012,8,26,12,27,26)"},{"v":18.46},{"v":18.3},null,{"v":15.76},{"v":16.22},null]},{"c":[{"v":"Date(2012,8,26,12,29,34)"},{"v":18.46},{"v":18.3},null,{"v":15.88},{"v":16.5},null]},{"c":[{"v":"Date(2012,8,26,12,31,41)"},{"v":18.44},{"v":18.3},null,{"v":16.0},{"v":16.82},null]},{"c":[{"v":"Date(2012,8,26,12,33,49)"},{"v":18.44},{"v":18.3},null,{"v":16.17},{"v":16.9},null]},{"c":[{"v":"Date(2012,8,26,12,35,58)"},{"v":18.44},{"v":18.3},null,{"v":16.31},{"v":16.77},null]},{"c":[{"v":"Date(2012,8,26,12,38,6)"},{"v":18.44},{"v":18.2},null,{"v":16.43},{"v":15.04},null]},{"c":[{"v":"Date(2012,8,26,12,40,14)"},{"v":18.44},{"v":18.2},null,{"v":16.36},{"v":15.01},null]},{"c":[{"v":"Date(2012,8,26,12,42,22)"},{"v":18.44},{"v":18.2},null,{"v":16.06},{"v":14.89},null]},{"c":[{"v":"Date(2012,8,26,12,44,30)"},{"v":18.43},{"v":18.2},null,{"v":15.6},{"v":14.73},null]},{"c":[{"v":"Date(2012,8,26,12,46,37)"},{"v":18.43},{"v":18.2},null,{"v":15.2},{"v":14.73},null]},{"c":[{"v":"Date(2012,8,26,12,48,45)"},{"v":18.4},{"v":18.2},null,{"v":15.01},{"v":15.19},null]},{"c":[{"v":"Date(2012,8,26,12,50,53)"},{"v":18.39},{"v":18.2},null,{"v":14.94},{"v":15.7},null]},{"c":[{"v":"Date(2012,8,26,12,53,1)"},{"v":18.38},{"v":18.2},null,{"v":14.94},{"v":16.13},null]},{"c":[{"v":"Date(2012,8,26,12,55,9)"},{"v":18.38},{"v":18.2},null,{"v":15.06},{"v":16.2},null]},{"c":[{"v":"Date(2012,8,26,12,57,14)"},{"v":18.38},{"v":18.2},null,{"v":15.17},{"v":16.1},null]},{"c":[{"v":"Date(2012,8,26,12,59,21)"},{"v":18.37},{"v":18.2},null,{"v":15.3},{"v":16.02},null]},{"c":[{"v":"Date(2012,8,26,13,1,29)"},{"v":18.37},{"v":18.2},null,{"v":15.46},{"v":16.07},null]},{"c":[{"v":"Date(2012,8,26,13,3,37)"},{"v":18.36},{"v":18.2},null,{"v":15.62},{"v":16.2},null]},{"c":[{"v":"Date(2012,8,26,13,5,46)"},{"v":18.34},{"v":18.1},null,{"v":15.76},{"v":15.07},null]},{"c":[{"v":"Date(2012,8,26,13,7,53)"},{"v":18.33},{"v":18.1},null,{"v":15.75},{"v":15.2},null]},{"c":[{"v":"Date(2012,8,26,13,10,1)"},{"v":18.32},{"v":18.1},null,{"v":15.49},{"v":15.52},null]},{"c":[{"v":"Date(2012,8,26,13,12,9)"},{"v":18.31},{"v":18.1},null,{"v":15.27},{"v":15.58},null]},{"c":[{"v":"Date(2012,8,26,13,14,17)"},{"v":18.31},{"v":18.1},null,{"v":15.19},{"v":15.48},null]},{"c":[{"v":"Date(2012,8,26,13,16,25)"},{"v":18.31},{"v":18.1},null,{"v":15.15},{"v":15.36},null]},{"c":[{"v":"Date(2012,8,26,13,18,32)"},{"v":18.31},{"v":18.1},null,{"v":15.21},{"v":15.31},null]},{"c":[{"v":"Date(2012,8,26,13,20,40)"},{"v":18.3},{"v":18.1},null,{"v":15.31},{"v":15.39},null]},{"c":[{"v":"Date(2012,8,26,13,22,48)"},{"v":18.28},{"v":18.1},null,{"v":15.44},{"v":15.83},null]},{"c":[{"v":"Date(2012,8,26,13,24,56)"},{"v":18.27},{"v":18.1},null,{"v":15.59},{"v":16.12},null]},{"c":[{"v":"Date(2012,8,26,13,27,3)"},{"v":18.26},{"v":18.1},null,{"v":15.75},{"v":16.43},null]},{"c":[{"v":"Date(2012,8,26,13,29,11)"},{"v":18.25},{"v":18.1},null,{"v":15.9},{"v":16.59},null]},{"c":[{"v":"Date(2012,8,26,13,31,19)"},{"v":18.25},{"v":18.1},null,{"v":16.06},{"v":16.49},null]},{"c":[{"v":"Date(2012,8,26,13,33,27)"},{"v":18.25},{"v":18.1},null,{"v":16.2},{"v":16.34},null]},{"c":[{"v":"Date(2012,8,26,13,35,36)"},{"v":18.25},{"v":18.0},null,{"v":16.31},{"v":14.67},null]},{"c":[{"v":"Date(2012,8,26,13,37,43)"},{"v":18.25},{"v":18.0},null,{"v":16.18},{"v":14.57},null]},{"c":[{"v":"Date(2012,8,26,13,39,51)"},{"v":18.24},{"v":18.0},null,{"v":15.79},{"v":14.53},null]},{"c":[{"v":"Date(2012,8,26,13,41,58)"},{"v":18.23},{"v":18.0},null,{"v":15.26},{"v":14.49},null]},{"c":[{"v":"Date(2012,8,26,13,44,6)"},{"v":18.22},{"v":18.0},null,{"v":14.83},{"v":14.65},null]},{"c":[{"v":"Date(2012,8,26,13,46,14)"},{"v":18.2},{"v":18.0},null,{"v":14.57},{"v":15.29},null]},{"c":[{"v":"Date(2012,8,26,13,48,22)"},{"v":18.19},{"v":18.0},null,{"v":14.5},{"v":15.78},null]},{"c":[{"v":"Date(2012,8,26,13,50,30)"},{"v":18.19},{"v":18.0},null,{"v":14.5},{"v":15.83},null]},{"c":[{"v":"Date(2012,8,26,13,52,37)"},{"v":18.18},{"v":18.0},null,{"v":14.61},{"v":15.79},null]},{"c":[{"v":"Date(2012,8,26,13,54,45)"},{"v":18.18},{"v":18.0},null,{"v":14.74},{"v":15.81},null]},{"c":[{"v":"Date(2012,8,26,13,56,53)"},{"v":18.16},{"v":18.0},null,{"v":14.87},{"v":16.13},null]},{"c":[{"v":"Date(2012,8,26,13,59,1)"},{"v":18.13},{"v":18.0},null,{"v":15.04},{"v":16.69},null]},{"c":[{"v":"Date(2012,8,26,14,1,9)"},{"v":18.13},{"v":18.0},null,{"v":15.19},{"v":16.84},null]},{"c":[{"v":"Date(2012,8,26,14,3,16)"},{"v":18.13},{"v":18.0},null,{"v":15.35},{"v":16.89},null]},{"c":[{"v":"Date(2012,8,26,14,5,24)"},{"v":18.13},{"v":18.0},null,{"v":15.51},{"v":16.8},null]},{"c":[{"v":"Date(2012,8,26,14,7,32)"},{"v":18.12},{"v":18.0},null,{"v":15.68},{"v":16.68},null]},{"c":[{"v":"Date(2012,8,26,14,9,40)"},{"v":18.12},{"v":18.0},null,{"v":15.82},{"v":16.57},null]},{"c":[{"v":"Date(2012,8,26,14,11,48)"},{"v":18.12},{"v":18.0},null,{"v":15.98},{"v":16.61},null]},{"c":[{"v":"Date(2012,8,26,14,13,56)"},{"v":18.11},{"v":18.0},null,{"v":16.12},{"v":16.67},null]},{"c":[{"v":"Date(2012,8,26,14,16,3)"},{"v":18.1},{"v":18.0},null,{"v":16.26},{"v":16.77},null]},{"c":[{"v":"Date(2012,8,26,14,18,11)"},{"v":18.08},{"v":18.0},null,{"v":16.4},{"v":17.13},null]},{"c":[{"v":"Date(2012,8,26,14,20,19)"},{"v":18.08},{"v":18.0},null,{"v":16.53},{"v":17.36},null]},{"c":[{"v":"Date(2012,8,26,14,22,27)"},{"v":18.08},{"v":18.0},null,{"v":16.67},{"v":17.36},null]},{"c":[{"v":"Date(2012,8,26,14,24,31)"},{"v":18.07},{"v":18.0},null,{"v":16.8},{"v":17.41},null]},{"c":[{"v":"Date(2012,8,26,14,26,38)"},{"v":18.07},{"v":18.0},null,{"v":16.91},{"v":17.38},null]},{"c":[{"v":"Date(2012,8,26,14,28,46)"},{"v":18.07},{"v":18.0},null,{"v":17.03},{"v":17.3},null]},{"c":[{"v":"Date(2012,8,26,14,30,54)"},{"v":18.06},{"v":18.0},null,{"v":17.13},{"v":17.4},null]},{"c":[{"v":"Date(2012,8,26,14,33,2)"},{"v":18.07},{"v":18.0},null,{"v":17.25},{"v":17.29},null]},{"c":[{"v":"Date(2012,8,26,14,35,10)"},{"v":18.07},{"v":18.0},null,{"v":17.37},{"v":17.16},null]},{"c":[{"v":"Date(2012,8,26,14,37,18)"},{"v":18.06},{"v":18.0},null,{"v":17.47},{"v":17.17},null]},{"c":[{"v":"Date(2012,8,26,14,39,26)"},{"v":18.06},{"v":18.0},null,{"v":17.56},{"v":17.11},null]},{"c":[{"v":"Date(2012,8,26,14,41,29)"},{"v":18.06},{"v":18.0},null,{"v":17.63},{"v":17.04},null]},{"c":[{"v":"Date(2012,8,26,14,43,35)"},{"v":18.06},{"v":18.0},null,{"v":17.58},{"v":16.97},null]},{"c":[{"v":"Date(2012,8,26,14,45,43)"},{"v":18.06},{"v":18.0},null,{"v":17.27},{"v":16.89},null]},{"c":[{"v":"Date(2012,8,26,14,47,55)"},{"v":18.06},{"v":18.0},null,{"v":16.87},{"v":16.84},null]},{"c":[{"v":"Date(2012,8,26,14,50,3)"},{"v":18.06},{"v":18.0},null,{"v":16.62},{"v":16.79},null]},{"c":[{"v":"Date(2012,8,26,14,52,11)"},{"v":18.06},{"v":18.0},null,{"v":16.44},{"v":16.84},null]},{"c":[{"v":"Date(2012,8,26,14,54,19)"},{"v":18.06},{"v":18.0},null,{"v":16.37},{"v":16.75},null]},{"c":[{"v":"Date(2012,8,26,14,56,27)"},{"v":18.04},{"v":18.0},null,{"v":16.32},{"v":16.98},null]},{"c":[{"v":"Date(2012,8,26,14,58,35)"},{"v":18.05},{"v":18.0},null,{"v":16.37},{"v":16.97},null]},{"c":[{"v":"Date(2012,8,26,15,0,43)"},{"v":18.04},{"v":18.0},null,{"v":16.42},{"v":17.24},null]},{"c":[{"v":"Date(2012,8,26,15,2,50)"},{"v":18.04},{"v":18.0},null,{"v":16.5},{"v":17.42},null]},{"c":[{"v":"Date(2012,8,26,15,4,58)"},{"v":18.03},{"v":18.0},null,{"v":16.58},{"v":17.58},null]},{"c":[{"v":"Date(2012,8,26,15,7,7)"},{"v":18.02},{"v":18.0},null,{"v":16.69},{"v":17.93},null]},{"c":[{"v":"Date(2012,8,26,15,9,15)"},{"v":18.02},{"v":18.0},null,{"v":16.81},{"v":18.18},null]},{"c":[{"v":"Date(2012,8,26,15,11,23)"},{"v":18.01},{"v":18.0},null,{"v":16.89},{"v":18.26},null]},{"c":[{"v":"Date(2012,8,26,15,13,31)"},{"v":18.0},{"v":18.0},null,{"v":17.0},{"v":18.27},null]},{"c":[{"v":"Date(2012,8,26,15,15,39)"},{"v":18.01},{"v":18.0},null,{"v":17.11},{"v":18.16},null]},{"c":[{"v":"Date(2012,8,26,15,17,47)"},{"v":18.01},{"v":18.0},null,{"v":17.21},{"v":18.13},null]},{"c":[{"v":"Date(2012,8,26,15,19,54)"},{"v":18.0},{"v":18.0},null,{"v":17.31},{"v":18.17},null]},{"c":[{"v":"Date(2012,8,26,15,22,2)"},{"v":18.0},{"v":18.0},null,{"v":17.39},{"v":18.1},null]},{"c":[{"v":"Date(2012,8,26,15,24,10)"},{"v":18.0},{"v":18.0},null,{"v":17.49},{"v":18.04},null]},{"c":[{"v":"Date(2012,8,26,15,26,18)"},{"v":18.0},{"v":18.0},null,{"v":17.56},{"v":18.04},null]},{"c":[{"v":"Date(2012,8,26,15,28,26)"},{"v":18.0},{"v":18.0},null,{"v":17.64},{"v":18.04},null]},{"c":[{"v":"Date(2012,8,26,15,30,34)"},{"v":18.0},{"v":18.0},null,{"v":17.74},{"v":18.02},null]},{"c":[{"v":"Date(2012,8,26,15,32,42)"},{"v":18.0},{"v":18.0},null,{"v":17.81},{"v":18.0},null]},{"c":[{"v":"Date(2012,8,26,15,34,50)"},{"v":18.0},{"v":18.0},null,{"v":17.9},{"v":17.99},null]},{"c":[{"v":"Date(2012,8,26,15,36,53)"},{"v":18.0},{"v":18.0},null,{"v":17.98},{"v":17.98},null]},{"c":[{"v":"Date(2012,8,26,15,39,1)"},{"v":18.0},{"v":18.0},null,{"v":18.06},{"v":17.97},null]},{"c":[{"v":"Date(2012,8,26,15,41,9)"},{"v":18.0},{"v":18.0},null,{"v":18.12},{"v":17.94},null]},{"c":[{"v":"Date(2012,8,26,15,43,17)"},{"v":18.0},{"v":18.0},null,{"v":18.18},{"v":17.96},null]},{"c":[{"v":"Date(2012,8,26,15,45,25)"},{"v":18.0},{"v":18.0},null,{"v":18.24},{"v":17.88},null]},{"c":[{"v":"Date(2012,8,26,15,47,33)"},{"v":18.0},{"v":18.0},null,{"v":18.29},{"v":17.94},null]},{"c":[{"v":"Date(2012,8,26,15,49,41)"},{"v":18.0},{"v":18.0},null,{"v":18.33},{"v":17.94},null]},{"c":[{"v":"Date(2012,8,26,15,51,49)"},{"v":18.0},{"v":18.0},null,{"v":18.38},{"v":17.89},null]},{"c":[{"v":"Date(2012,8,26,15,53,57)"},{"v":18.0},{"v":18.0},null,{"v":18.44},{"v":17.91},null]},{"c":[{"v":"Date(2012,8,26,15,56,5)"},{"v":18.0},{"v":18.0},null,{"v":18.49},{"v":17.91},null]},{"c":[{"v":"Date(2012,8,26,15,58,12)"},{"v":18.0},{"v":18.0},null,{"v":18.52},{"v":17.9},null]},{"c":[{"v":"Date(2012,8,26,16,0,19)"},{"v":18.0},{"v":18.0},null,{"v":18.56},{"v":17.86},null]},{"c":[{"v":"Date(2012,8,26,16,2,27)"},{"v":18.01},{"v":18.0},null,{"v":18.61},{"v":17.79},null]},{"c":[{"v":"Date(2012,8,26,16,4,35)"},{"v":18.01},{"v":18.0},null,{"v":18.63},{"v":17.8},null]},{"c":[{"v":"Date(2012,8,26,16,6,43)"},{"v":18.01},{"v":18.0},null,{"v":18.64},{"v":17.74},null]},{"c":[{"v":"Date(2012,8,26,16,8,51)"},{"v":18.01},{"v":18.0},null,{"v":18.69},{"v":17.64},null]},{"c":[{"v":"Date(2012,8,26,16,10,59)"},{"v":18.01},{"v":18.0},null,{"v":18.69},{"v":17.68},null]},{"c":[{"v":"Date(2012,8,26,16,13,7)"},{"v":18.02},{"v":18.0},null,{"v":18.71},{"v":17.52},null]},{"c":[{"v":"Date(2012,8,26,16,15,15)"},{"v":18.01},{"v":18.0},null,{"v":18.75},{"v":17.7},null]},{"c":[{"v":"Date(2012,8,26,16,17,23)"},{"v":18.02},{"v":18.0},null,{"v":18.75},{"v":17.48},null]},{"c":[{"v":"Date(2012,8,26,16,19,31)"},{"v":18.03},{"v":18.0},null,{"v":18.76},{"v":17.4},null]},{"c":[{"v":"Date(2012,8,26,16,21,38)"},{"v":18.03},{"v":18.0},null,{"v":18.8},{"v":17.3},null]},{"c":[{"v":"Date(2012,8,26,16,23,46)"},{"v":18.04},{"v":18.0},null,{"v":18.81},{"v":17.02},null]},{"c":[{"v":"Date(2012,8,26,16,25,54)"},{"v":18.03},{"v":18.0},null,{"v":18.81},{"v":17.26},null]},{"c":[{"v":"Date(2012,8,26,16,28,2)"},{"v":18.04},{"v":18.0},null,{"v":18.71},{"v":17.22},null]},{"c":[{"v":"Date(2012,8,26,16,30,10)"},{"v":18.04},{"v":18.0},null,{"v":18.4},{"v":17.13},null]},{"c":[{"v":"Date(2012,8,26,16,32,18)"},{"v":18.04},{"v":18.0},null,{"v":17.85},{"v":17.31},null]},{"c":[{"v":"Date(2012,8,26,16,34,26)"},{"v":18.04},{"v":18.0},null,{"v":17.29},{"v":17.26},null]},{"c":[{"v":"Date(2012,8,26,16,36,34)"},{"v":18.03},{"v":18.0},null,{"v":16.89},{"v":17.55},null]},{"c":[{"v":"Date(2012,8,26,16,38,42)"},{"v":18.02},{"v":18.0},null,{"v":16.63},{"v":17.88},null]},{"c":[{"v":"Date(2012,8,26,16,40,50)"},{"v":18.03},{"v":18.0},null,{"v":16.48},{"v":17.81},null]},{"c":[{"v":"Date(2012,8,26,16,42,58)"},{"v":18.02},{"v":18.0},null,{"v":16.44},{"v":18.0},null]},{"c":[{"v":"Date(2012,8,26,16,45,6)"},{"v":18.01},{"v":18.0},null,{"v":16.44},{"v":18.2},null]},{"c":[{"v":"Date(2012,8,26,16,47,14)"},{"v":18.01},{"v":18.0},null,{"v":16.48},{"v":18.2},null]},{"c":[{"v":"Date(2012,8,26,16,49,22)"},{"v":18.0},{"v":18.0},null,{"v":16.55},{"v":18.33},null]},{"c":[{"v":"Date(2012,8,26,16,51,30)"},{"v":18.0},{"v":18.0},null,{"v":16.62},{"v":18.28},null]},{"c":[{"v":"Date(2012,8,26,16,53,38)"},{"v":18.0},{"v":18.0},null,{"v":16.7},{"v":18.23},null]},{"c":[{"v":"Date(2012,8,26,16,55,46)"},{"v":18.0},{"v":18.0},null,{"v":16.81},{"v":18.19},null]},{"c":[{"v":"Date(2012,8,26,16,57,54)"},{"v":18.0},{"v":18.0},null,{"v":16.92},{"v":18.14},null]},{"c":[{"v":"Date(2012,8,26,17,0,2)"},{"v":18.0},{"v":18.0},null,{"v":17.0},{"v":18.16},null]},{"c":[{"v":"Date(2012,8,26,17,2,10)"},{"v":18.0},{"v":18.0},null,{"v":17.12},{"v":18.07},null]},{"c":[{"v":"Date(2012,8,26,17,4,18)"},{"v":18.0},{"v":18.0},null,{"v":17.19},{"v":18.09},null]},{"c":[{"v":"Date(2012,8,26,17,6,26)"},{"v":18.0},{"v":18.0},null,{"v":17.29},{"v":18.11},null]},{"c":[{"v":"Date(2012,8,26,17,8,34)"},{"v":18.0},{"v":18.0},null,{"v":17.37},{"v":18.1},null]},{"c":[{"v":"Date(2012,8,26,17,10,42)"},{"v":17.99},{"v":18.0},null,{"v":17.44},{"v":18.13},null]},{"c":[{"v":"Date(2012,8,26,17,12,50)"},{"v":18.0},{"v":18.0},null,{"v":17.5},{"v":18.05},null]},{"c":[{"v":"Date(2012,8,26,17,14,58)"},{"v":17.99},{"v":18.0},null,{"v":17.59},{"v":18.11},null]},{"c":[{"v":"Date(2012,8,26,17,17,6)"},{"v":17.99},{"v":18.0},null,{"v":17.68},{"v":18.1},null]},{"c":[{"v":"Date(2012,8,26,17,19,14)"},{"v":18.0},{"v":18.0},null,{"v":17.75},{"v":18.06},null]},{"c":[{"v":"Date(2012,8,26,17,21,22)"},{"v":17.99},{"v":18.0},null,{"v":17.84},{"v":18.11},null]},{"c":[{"v":"Date(2012,8,26,17,23,30)"},{"v":17.99},{"v":18.0},null,{"v":17.93},{"v":18.2},null]},{"c":[{"v":"Date(2012,8,26,17,25,39)"},{"v":18.0},{"v":18.0},null,{"v":17.99},{"v":18.06},null]},{"c":[{"v":"Date(2012,8,26,17,27,47)"},{"v":17.99},{"v":18.0},null,{"v":18.06},{"v":18.07},null]},{"c":[{"v":"Date(2012,8,26,17,29,55)"},{"v":17.99},{"v":18.0},null,{"v":18.12},{"v":18.12},null]},{"c":[{"v":"Date(2012,8,26,17,32,3)"},{"v":18.0},{"v":18.0},null,{"v":18.18},{"v":18.08},null]},{"c":[{"v":"Date(2012,8,26,17,34,11)"},{"v":18.0},{"v":18.0},null,{"v":18.23},{"v":18.03},null]},{"c":[{"v":"Date(2012,8,26,17,36,19)"},{"v":18.0},{"v":18.0},null,{"v":18.29},{"v":18.06},null]},{"c":[{"v":"Date(2012,8,26,17,38,27)"},{"v":18.0},{"v":18.0},null,{"v":18.32},{"v":18.05},null]},{"c":[{"v":"Date(2012,8,26,17,40,35)"},{"v":18.0},{"v":18.0},null,{"v":18.37},{"v":18.06},null]},{"c":[{"v":"Date(2012,8,26,17,42,43)"},{"v":18.0},{"v":18.0},null,{"v":18.43},{"v":18.02},null]},{"c":[{"v":"Date(2012,8,26,17,44,51)"},{"v":18.0},{"v":18.0},null,{"v":18.44},{"v":18.03},null]},{"c":[{"v":"Date(2012,8,26,17,46,59)"},{"v":18.0},{"v":18.0},null,{"v":18.5},{"v":18.01},null]},{"c":[{"v":"Date(2012,8,26,17,49,7)"},{"v":18.0},{"v":18.0},null,{"v":18.53},{"v":18.0},null]},{"c":[{"v":"Date(2012,8,26,17,51,15)"},{"v":18.0},{"v":18.0},null,{"v":18.56},{"v":18.0},null]},{"c":[{"v":"Date(2012,8,26,17,53,23)"},{"v":18.0},{"v":18.0},null,{"v":18.59},{"v":18.03},null]},{"c":[{"v":"Date(2012,8,26,17,55,31)"},{"v":18.0},{"v":18.0},null,{"v":18.62},{"v":18.01},null]},{"c":[{"v":"Date(2012,8,26,17,57,39)"},{"v":18.0},{"v":18.0},null,{"v":18.63},{"v":17.96},null]},{"c":[{"v":"Date(2012,8,26,17,59,47)"},{"v":18.0},{"v":18.0},null,{"v":18.66},{"v":17.98},null]},{"c":[{"v":"Date(2012,8,26,18,1,55)"},{"v":18.0},{"v":18.0},null,{"v":18.69},{"v":17.98},null]},{"c":[{"v":"Date(2012,8,26,18,4,3)"},{"v":18.0},{"v":18.0},null,{"v":18.69},{"v":17.99},null]}],"cols":[{"type":"datetime","id":"Time","label":"Time"},{"type":"number","id":"BeerTemp","label":"Beer temperature"},{"type":"number","id":"BeerSet","label":"Beer setting"},{"type":"string","id":"BeerAnn","label":"Beer Annotate"},{"type":"number","id":"FridgeTemp","label":"Fridge temperature"},{"type":"number","id":"FridgeSet","label":"Fridge setting"},{"type":"string","id":"FridgeAnn","label":"Fridge Annotate"}]}